[
  {
    "model": "products.PackageLevel",
    "pk": 10,
    "fields": {
      "level": "Transport load",
      "unit_descriptor": "TRANSPORT_LOAD"
    }
  },
  {
    "model": "products.PackageLevel",
    "pk": 20,
    "fields": {
      "level": "Mixed module",
      "unit_descriptor": "MIXED_MODULE"
    }
  },
  {
    "model": "products.PackageLevel",
    "pk": 30,
    "fields": {
      "level": "Pallet e.g. pallet of cases of beer",
      "unit_descriptor": "PALLET"
    }
  },
  {
    "model": "products.PackageLevel",
    "pk": 40,
    "fields": {
      "level": "Display shipper",
      "unit_descriptor": "DISPLAY_SHIPPER"
    }
  },
  {
    "model": "products.PackageLevel",
    "pk": 50,
    "fields": {
      "level": "Outer Case e.g. case of beer (bottles or packs)",
      "unit_descriptor": "CASE"
    }
  },
  {
    "model": "products.PackageLevel",
    "pk": 60,
    "fields": {
      "level": "Pack or Inner Pack e.g. six pack of beer bottles",
      "unit_descriptor": "PACK_OR_INNER_PACK"
    }
  },
  {
    "model": "products.PackageLevel",
    "pk": 70,
    "fields": {
      "level": "Consumer Unit (Base Unit/Each) e.g. bottle of beer",
      "unit_descriptor": "BASE_UNIT_OR_EACH"
    }
  }
]
